Workbook

Sheet Comparatif
A1: Smart Tontine — Quel modèle économique est rentable ?
A2: Validation sur 5 ans (2027-2031), Burkina Faso puis sous-région · M FCFA sauf mention contraire
A4: Critère | B4: Seuil de validation | C4: A — Commission seule | D4: B — Transactionnel | E4: C — Freemium abonnements | F4: D — Tontine + microfinance | G4: E — B2B pour les SFD | H4: F — Hybride Smart Tontine | I4: G — Hybride optimisé (recommandé)
A5: Chiffre d'affaires 2031 | B5: — | C5: =Modèles!G21 -> 523162800 | D5: =Modèles!G59 -> 799048800 | E5: =Modèles!G97 -> 274528800 | F5: =Modèles!G135 -> 848147220 | G5: =Modèles!G173 -> 242500000 | H5: =Modèles!G211 -> 1096102820 | I5: =Modèles!G249 -> 1217352820
A6: EBITDA 2031 | B6: > 0 | C6: =Modèles!G36 -> -581789350 | D6: =Modèles!G74 -> -305903350 | E6: =Modèles!G112 -> -439364350 | F6: =Modèles!G150 -> -314521780 | G6: =Modèles!G188 -> -142750000 | H6: =Modèles!G226 -> -100671180 | I6: =Modèles!G264 -> 191035420
A7: Marge d'EBITDA 2031 | B7: ≥ 15 % | C7: =IF(Modèles!G21=0,0,Modèles!G36/Modèles!G21) -> -1.1120618 | D7: =IF(Modèles!G59=0,0,Modèles!G74/Modèles!G59) -> -0.38283438 | E7: =IF(Modèles!G97=0,0,Modèles!G112/Modèles!G97) -> -1.6004308 | F7: =IF(Modèles!G135=0,0,Modèles!G150/Modèles!G135) -> -0.37083395 | G7: =IF(Modèles!G173=0,0,Modèles!G188/Modèles!G173) -> -0.58865979 | H7: =IF(Modèles!G211=0,0,Modèles!G226/Modèles!G211) -> -0.09184465 | I7: =IF(Modèles!G249=0,0,Modèles!G264/Modèles!G249) -> 0.15692691
A8: EBITDA cumulé 2027-2031 | B8: — | C8: =SUM(Modèles!C36:G36) -> -1692382325 | D8: =SUM(Modèles!C74:G74) -> -1122730475 | E8: =SUM(Modèles!C112:G112) -> -1358446550 | F8: =SUM(Modèles!C150:G150) -> -1186204835 | G8: =SUM(Modèles!C188:G188) -> -724550000 | H8: =SUM(Modèles!C226:G226) -> -828781035 | I8: =SUM(Modèles!C264:G264) -> -175764925
A9: Première année d'EBITDA positif | B9: ≤ 2029 | C9: =IFERROR(INDEX(Modèles!$C$4:$G$4,MATCH(1,Modèles!C40:G40,0)),"jamais") -> jamais | D9: =IFERROR(INDEX(Modèles!$C$4:$G$4,MATCH(1,Modèles!C78:G78,0)),"jamais") -> jamais | E9: =IFERROR(INDEX(Modèles!$C$4:$G$4,MATCH(1,Modèles!C116:G116,0)),"jamais") -> jamais | F9: =IFERROR(INDEX(Modèles!$C$4:$G$4,MATCH(1,Modèles!C154:G154,0)),"jamais") -> jamais | G9: =IFERROR(INDEX(Modèles!$C$4:$G$4,MATCH(1,Modèles!C192:G192,0)),"jamais") -> jamais | H9: =IFERROR(INDEX(Modèles!$C$4:$G$4,MATCH(1,Modèles!C230:G230,0)),"jamais") -> jamais | I9: =IFERROR(INDEX(Modèles!$C$4:$G$4,MATCH(1,Modèles!C268:G268,0)),"jamais") -> 2030
A10: Besoin de financement (creux de trésorerie) | B10: ≤ 600 M F | C10: =-MIN(0,MIN(Modèles!C39:G39)) -> 1737382325 | D10: =-MIN(0,MIN(Modèles!C77:G77)) -> 1167730475 | E10: =-MIN(0,MIN(Modèles!C115:G115)) -> 1403446550 | F10: =-MIN(0,MIN(Modèles!C153:G153)) -> 1231204835 | G10: =-MIN(0,MIN(Modèles!C191:G191)) -> 769550000 | H10: =-MIN(0,MIN(Modèles!C229:G229)) -> 873781035 | I10: =-MIN(0,MIN(Modèles!C267:G267)) -> 426846485
A11: Marge par membre et par an (2031, hors acquisition) | B11: > 0 F | C11: =Modèles!G41 -> 90.277872 | D11: =Modèles!G79 -> 1135.4194 | E11: =Modèles!G117 -> 716.08762 | F11: =Modèles!G155 -> 1216.4194 | G11: =Modèles!G193 -> 835 | H11: =Modèles!G231 -> 1419.5923 | I11: =Modèles!G269 -> 1599.4813
A12: VAN des flux 2027-2031 (20 %, sans valeur terminale) | B12: — | C12: =NPV(Hypothèses!$C$54,Modèles!C38:G38) -> -9.3718208e+08 | D12: =NPV(Hypothèses!$C$54,Modèles!C76:G76) -> -6.6568255e+08 | E12: =NPV(Hypothèses!$C$54,Modèles!C114:G114) -> -7.7383385e+08 | F12: =NPV(Hypothèses!$C$54,Modèles!C152:G152) -> -7.0049933e+08 | G12: =NPV(Hypothèses!$C$54,Modèles!C190:G190) -> -4.6757385e+08 | H12: =NPV(Hypothèses!$C$54,Modèles!C228:G228) -> -5.4685787e+08 | I12: =NPV(Hypothèses!$C$54,Modèles!C266:G266) -> -2.4898583e+08
A13: VERDICT STRICT (EBITDA positif ≤ 2029 + tous les seuils) | C13: =IF(AND(C6>0,C7>=0.15,IFERROR(VALUE(C9)<=2029,FALSE()),C10<=600000000,C11>0),"✔ RENTABLE","✘ NON VALIDÉ") -> ✘ NON VALIDÉ | D13: =IF(AND(D6>0,D7>=0.15,IFERROR(VALUE(D9)<=2029,FALSE()),D10<=600000000,D11>0),"✔ RENTABLE","✘ NON VALIDÉ") -> ✘ NON VALIDÉ | E13: =IF(AND(E6>0,E7>=0.15,IFERROR(VALUE(E9)<=2029,FALSE()),E10<=600000000,E11>0),"✔ RENTABLE","✘ NON VALIDÉ") -> ✘ NON VALIDÉ | F13: =IF(AND(F6>0,F7>=0.15,IFERROR(VALUE(F9)<=2029,FALSE()),F10<=600000000,F11>0),"✔ RENTABLE","✘ NON VALIDÉ") -> ✘ NON VALIDÉ | G13: =IF(AND(G6>0,G7>=0.15,IFERROR(VALUE(G9)<=2029,FALSE()),G10<=600000000,G11>0),"✔ RENTABLE","✘ NON VALIDÉ") -> ✘ NON VALIDÉ | H13: =IF(AND(H6>0,H7>=0.15,IFERROR(VALUE(H9)<=2029,FALSE()),H10<=600000000,H11>0),"✔ RENTABLE","✘ NON VALIDÉ") -> ✘ NON VALIDÉ | I13: =IF(AND(I6>0,I7>=0.15,IFERROR(VALUE(I9)<=2029,FALSE()),I10<=600000000,I11>0),"✔ RENTABLE","✘ NON VALIDÉ") -> ✘ NON VALIDÉ
A14: VERDICT INVESTISSEUR (EBITDA positif ≤ 2030, autres seuils identiques) | C14: =IF(AND(C6>0,C7>=0.15,IFERROR(VALUE(C9)<=2030,FALSE()),C10<=600000000,C11>0),"✔ RENTABLE","✘ NON VALIDÉ") -> ✘ NON VALIDÉ | D14: =IF(AND(D6>0,D7>=0.15,IFERROR(VALUE(D9)<=2030,FALSE()),D10<=600000000,D11>0),"✔ RENTABLE","✘ NON VALIDÉ") -> ✘ NON VALIDÉ | E14: =IF(AND(E6>0,E7>=0.15,IFERROR(VALUE(E9)<=2030,FALSE()),E10<=600000000,E11>0),"✔ RENTABLE","✘ NON VALIDÉ") -> ✘ NON VALIDÉ | F14: =IF(AND(F6>0,F7>=0.15,IFERROR(VALUE(F9)<=2030,FALSE()),F10<=600000000,F11>0),"✔ RENTABLE","✘ NON VALIDÉ") -> ✘ NON VALIDÉ | G14: =IF(AND(G6>0,G7>=0.15,IFERROR(VALUE(G9)<=2030,FALSE()),G10<=600000000,G11>0),"✔ RENTABLE","✘ NON VALIDÉ") -> ✘ NON VALIDÉ | H14: =IF(AND(H6>0,H7>=0.15,IFERROR(VALUE(H9)<=2030,FALSE()),H10<=600000000,H11>0),"✔ RENTABLE","✘ NON VALIDÉ") -> ✘ NON VALIDÉ | I14: =IF(AND(I6>0,I7>=0.15,IFERROR(VALUE(I9)<=2030,FALSE()),I10<=600000000,I11>0),"✔ RENTABLE","✘ NON VALIDÉ") -> ✔ RENTABLE
A16: Lecture
A17: Les six modèles partagent le même déploiement (Burkina 2027 → Côte d'Ivoire → Mali → Niger/Sénégal → Bénin/Togo) et les mêmes coûts ; seuls les leviers de revenus diffèrent.
A18: Seuils fixés avant le calcul : EBITDA 2031 > 0 et marge ≥ 15 %, besoin de financement ≤ 600 M F (atteignable en pré-amorçage + amorçage), marge par membre positive, EBITDA positif en année 3 (strict) ou 4 (investisseur).
A19: Les hypothèses jaunes de l'onglet Hypothèses (coût Mobile Money, recirculation, adoption, pertes de crédit, prix des licences SFD) sont à valider par un pilote avant la levée.

Sheet Hypothèses
A1: Smart Tontine — Hypothèses
A2: Cellules bleues = saisies · fond jaune = hypothèses clés à valider sur le terrain · montants en FCFA
A3: Toutes les valeurs sont des hypothèses de travail (ordres de grandeur) à confirmer : sources et statut dans la colonne commentaire.
A5: 1. Pays et calendrier de déploiement
A6: Pays | B6: Année de lancement | C6: Adultes 15+ (millions) | D6: Coefficient de marché | E6: Cotisation mensuelle moyenne (F) | F6: Commentaire
A7: Burkina Faso | B7: 2027 | C7: 12.9 | D7: 1 | E7: 12500 | F7: Pays de lancement. ≈ 23-24 M d'habitants (projections INSD, à confirmer) ; Orange Money, Moov Money, Wave, Sank Money.
A8: Côte d'Ivoire | B8: 2029 | C8: 18 | D8: 0.7 | E8: 20000 | F8: Forte communauté burkinabè (tontines et transferts transfrontaliers) ; concurrence plus forte.
A9: Mali | B9: 2030 | C9: 12 | D9: 0.7 | E9: 12500 | F9: Proche du Burkina (AES, UEMOA) ; risque sécuritaire.
A10: Niger | B10: 2031 | C10: 12.5 | D10: 0.6 | E10: 10000 | F10: Idem ; marché Mobile Money moins mûr.
A11: Sénégal | B11: 2031 | C11: 10.5 | D11: 0.5 | E11: 20000 | F11: Concurrents installés (Maman Tontine, MaTontine) : coefficient réduit.
A12: Bénin / Togo | B12: 2032 | C12: 13 | D12: 0.7 | E12: 15000 | F12: Deux marchés regroupés.
A14: 2. Hypothèses par année (colonnes = années ; pour la courbe d'adoption, colonnes = années depuis le lancement)
A15: Hypothèse | B15: Unité | C15: 2027 | D15: 2028 | E15: 2029 | F15: 2030 | G15: 2031 | H15: Commentaire
A16: Membres actifs / adultes, par année depuis le lancement (1 à 5) | B16: % | C16: 0.0006 | D16: 0.0023 | E16: 0.0055 | F16: 0.009 | G16: 0.013 | H16: Burkina A5 ≈ 168 000 membres actifs (1,3 % des adultes). Référence : Maman Tontine revendique 30 000+ utilisateurs au Sénégal.
A17: Part des cotisations payées depuis le solde Smart Tontine | B17: % | C17: 0.15 | D17: 0.25 | E17: 0.3 | F17: 0.35 | G17: 0.4 | H17: Argent qui ne ressort pas : pot gardé pour le tour suivant, avance, épargne. Évite les frais opérateurs d'entrée et de sortie.
A18: Membres empruntant dans l'année (avance ou microcrédit) | B18: % | C18: 0.03 | D18: 0.06 | E18: 0.1 | F18: 0.12 | G18: 0.14
A19: Membres de SFD partenaires gérés sur la plateforme (canal B2B) | B19: membres | C19: 5000 | D19: 30000 | E19: 80000 | F19: 150000 | G19: 250000 | H19: Tontines et groupes d'épargne des SFD partenaires numérisés en marque blanche (≈ 1,47 M de comptes SFD au Burkina en 2024).
A20: Effectif siège (ETP) | B20: ETP | C20: 8 | D20: 12 | E20: 16 | F20: 20 | G20: 24 | H20: Hors équipes pays (comptées dans le coût fixe par pays).
A21: Montée en charge de l'équipe crédit | B21: % | C21: 0 | D21: 0.5 | E21: 1 | F21: 1 | G21: 1 | H21: Le crédit démarre en 2028 (pilote) : pas d'équipe crédit complète avant.
A23: 3. Hypothèses constantes
A24: Coût d'encaissement Mobile Money (payé par la plateforme) | B24: % | C24: 0.01 | H24: À négocier avec Orange Money, Moov, Wave ; agrégateurs locaux (ex. Senfenico) 1-2 %. HYPOTHÈSE CRITIQUE.
A25: Coût de décaissement vers Mobile Money | B25: % | C25: 0.005
A26: SMS et notifications par membre et par an | B26: F | C26: 150 | H26: Push et WhatsApp en priorité ; SMS seulement pour l'OTP et les membres sans smartphone.
A27: Hébergement et services par membre et par an | B27: F | C27: 120
A28: Coût KYC par nouveau membre vérifié | B28: F | C28: 250 | H28: 50 % des nouveaux membres vérifiés.
A29: Part des nouveaux membres vérifiés | B29: % | C29: 0.5
A30: Taille moyenne d'une tontine / d'un groupe | B30: membres | C30: 12
A31: Abonnement « Organisateur Pro » (par mois) | B31: F | C31: 2000 | H31: Pour trésoriers de tontines, associations, GIE : tableau de bord, relances, exports, plusieurs groupes.
A32: Abonnement membre « Smart Tontine+ » (par mois) | B32: F | C32: 500 | H32: Retrait du pot offert, avance à taux réduit, support prioritaire.
A33: Solde moyen conservé par membre actif | B33: F | C33: 8000 | H33: Base du float.
A34: Rendement du float (compte de cantonnement / dépôt à terme) | B34: % | C34: 0.03 | H34: À négocier avec la banque ou le SFD partenaire.
A35: Crédit moyen (avance ou microcrédit) | B35: F | C35: 50000
A36: Intérêts perçus sur la durée du crédit (% du montant) | B36: % | C36: 0.045 | H36: 1,5 % par mois × 3 mois en moyenne, sous le taux d'usure.
A37: Part des intérêts revenant à Smart Tontine | B37: % | C37: 0.4 | H37: Le SFD partenaire finance et porte le crédit.
A38: Pertes sur crédits (% des montants versés) | B38: % | C38: 0.03 | H38: Prudence : le secteur SFD burkinabè a vu son résultat baisser de 34,8 % en 2024 (BCEAO) ; avances adossées au pot moins risquées.
A39: Part des pertes garantie par Smart Tontine | B39: % | C39: 0.5
A40: Frais d'apport sur crédit accordé via le canal SFD (payés par le SFD) | B40: % | C40: 0.01
A41: Membres souscrivant une micro-assurance | B41: % | C41: 0.1 | H41: Assurance décès / santé des membres de tontine (partenaire assureur).
A42: Prime annuelle moyenne | B42: F | C42: 3000
A43: Commission de distribution d'assurance | B43: % | C43: 0.2
A44: Licence SFD : prix par membre géré et par mois | B44: F | C44: 75 | H44: Payé par le SFD. Plafonné par sa rentabilité : ≈ 3 Mds F de résultat pour 1,47 M de comptes en 2024 (BCEAO), soit ≈ 2 000 F/compte/an.
A45: Cotisation mensuelle moyenne d'un membre SFD | B45: F | C45: 10000
A46: Coût annuel chargé moyen d'un ETP siège | B46: F | C46: 6000000 | H46: ≈ 500 000 F/mois chargés (Ouagadougou).
A47: Coût fixe annuel par pays ouvert | B47: F | C47: 45000000 | H47: Responsable pays, 2-3 animateurs, bureau, juridique, frais partenaires.
A48: Marketing de marque par pays ouvert et par an | B48: F | C48: 12000000
A49: Charges fixes siège (tech, audit, sécurité, loyer) | B49: F | C49: 40000000
A50: Équipe crédit et risques (si crédit) | B50: F | C50: 30000000
A51: Équipe ventes et intégration SFD (si B2B) | B51: F | C51: 25000000
A52: Investissement de lancement | B52: F | C52: 45000000 | H52: Plateforme déjà développée (ce dépôt) : durcissement, audit de sécurité, intégrations opérateurs.
A53: Impôt sur les sociétés | B53: % | C53: 0.275 | H53: Taux IS Burkina Faso 27,5 % (à confirmer).
A54: Taux d'actualisation (VAN) | B54: % | C54: 0.2 | H54: Exigence d'un investisseur early-stage en Afrique de l'Ouest.
A56: 4. Les 6 modèles économiques testés (une colonne par modèle)
A57: Paramètre | C57: A — Commission seule | D57: B — Transactionnel | E57: C — Freemium abonnements | F57: D — Tontine + microfinance | G57: E — B2B pour les SFD | H57: F — Hybride Smart Tontine | I57: G — Hybride optimisé (recommandé)
A58: Canal B2C (application grand public) actif | C58: 1 | D58: 1 | E58: 1 | F58: 1 | G58: 0 | H58: 1 | I58: 1
A59: Commission sur chaque pot versé | C59: 0.01 | D59: 0.01 | E59: 0 | F59: 0.01 | G59: 0 | H59: 0.01 | I59: 0.01
A60: Frais sur les retraits vers Mobile Money | C60: 0 | D60: 0.01 | E60: 0 | F60: 0.01 | G60: 0 | H60: 0.01 | I60: 0.01
A61: Frais opérateurs refacturés au membre (1 = oui) | C61: 0 | D61: 0 | E61: 1 | F61: 0 | G61: 1 | H61: 0 | I61: 0 | J61: C et E : le membre (ou le SFD) paie les frais Mobile Money au coût réel.
A62: Groupes abonnés Organisateur Pro | C62: 0 | D62: 0 | E62: 0.25 | F62: 0 | G62: 0 | H62: 0.15 | I62: 0.15
A63: Membres abonnés Smart Tontine+ | C63: 0 | D63: 0 | E63: 0.05 | F63: 0 | G63: 0 | H63: 0.03 | I63: 0.03
A64: Revenus du float (1 = oui) | C64: 1 | D64: 1 | E64: 1 | F64: 1 | G64: 0 | H64: 1 | I64: 1
A65: Crédit via SFD partenaire (1 = oui) | C65: 0 | D65: 0 | E65: 0 | F65: 1 | G65: 0 | H65: 1 | I65: 1
A66: Micro-assurance (1 = oui) | C66: 0 | D66: 0 | E66: 0 | F66: 1 | G66: 0 | H66: 1 | I66: 1
A67: Part du potentiel B2B SFD captée | C67: 0 | D67: 0 | E67: 0 | F67: 0 | G67: 1 | H67: 0.5 | I67: 1
A68: Coût d'acquisition par nouveau membre B2C (F) | C68: 1200 | D68: 1200 | E68: 1400 | F68: 1200 | G68: 0 | H68: 1000 | I68: 1000 | J68: F : moins cher grâce aux organisateurs Pro qui recrutent leur groupe (commission parrainage incluse).
A69: Coût d'acquisition par membre B2B (formation, lancement chez le SFD) | C69: 0 | D69: 0 | E69: 0 | F69: 0 | G69: 300 | H69: 300 | I69: 300
A70: Levier : réduction des frais Mobile Money | C70: 0 | D70: 0 | E70: 0 | F70: 0 | G70: 0 | H70: 0 | I70: 0.4 | J70: G : cotisations prélevées sur le compte d'épargne SFD (pas de frais opérateur) + tarifs négociés (objectif ≤ 0,7 % / 0,3 %).
A71: Levier : points de recirculation en plus | C71: 0 | D71: 0 | E71: 0 | F71: 0 | G71: 0 | H71: 0 | I71: 0 | J71: Testé : neutre sur la rentabilité (les frais de retrait compensent les frais opérateurs évités) ; utile pour la fidélisation, pas pour la marge.
A72: Levier : réduction des coûts siège | C72: 0 | D72: 0 | E72: 0 | F72: 0 | G72: 0 | H72: 0 | I72: 0.2 | J72: G : équipe siège resserrée (Ouagadougou), tech mutualisée, fonctions support partagées avec le SFD.
A74: A — Commission seule | C74: Clone de Maman Tontine : 1 % sur chaque pot, retrait gratuit, frais opérateurs à la charge de la plateforme.
A75: B — Transactionnel | C75: 1 % sur les pots + 1 % sur les retraits vers Mobile Money + float.
A76: C — Freemium abonnements | C76: Gratuit pour les membres (frais opérateurs refacturés au coût), revenus = abonnements Organisateur Pro et Smart Tontine+.
A77: D — Tontine + microfinance | C77: B + part des intérêts de crédit (SFD partenaire) + micro-assurance.
A78: E — B2B pour les SFD | C78: Plateforme en marque blanche vendue aux SFD : licence par membre + frais d'apport de crédit. Pas de B2C.
A79: F — Hybride Smart Tontine | C79: D + abonnements Organisateur Pro / Smart Tontine+ + canal B2B SFD (à moitié de E).
A80: G — Hybride optimisé (recommandé) | C80: F + trois leviers structurels : cotisations prélevées sur le compte SFD et tarifs opérateurs négociés (−40 % de frais Mobile Money), siège resserré à Ouagadougou (−20 % de coûts siège), canal SFD exploité à 100 %.

Sheet Déploiement
A1: Smart Tontine — Déploiement pays par pays (canal B2C)
A2: Membres actifs = adultes × courbe d'adoption (selon l'ancienneté du pays) × coefficient de marché
A4: Pays / indicateur | B4: Unité | C4: 2027 | D4: 2028 | E4: 2029 | F4: 2030 | G4: 2031
A5: Burkina Faso
A6: Ancienneté (années) | C6: =MAX(0,2027-Hypothèses!$B$7+1) -> 1 | D6: =MAX(0,2028-Hypothèses!$B$7+1) -> 2 | E6: =MAX(0,2029-Hypothèses!$B$7+1) -> 3 | F6: =MAX(0,2030-Hypothèses!$B$7+1) -> 4 | G6: =MAX(0,2031-Hypothèses!$B$7+1) -> 5
A7: Membres actifs | B7: membres | C7: =IF(C6=0,0,Hypothèses!$C$7*1000000*INDEX(Hypothèses!$C$16:$G$16,1,MIN(5,C6))*Hypothèses!$D$7) -> 7740 | D7: =IF(D6=0,0,Hypothèses!$C$7*1000000*INDEX(Hypothèses!$C$16:$G$16,1,MIN(5,D6))*Hypothèses!$D$7) -> 29670 | E7: =IF(E6=0,0,Hypothèses!$C$7*1000000*INDEX(Hypothèses!$C$16:$G$16,1,MIN(5,E6))*Hypothèses!$D$7) -> 70950 | F7: =IF(F6=0,0,Hypothèses!$C$7*1000000*INDEX(Hypothèses!$C$16:$G$16,1,MIN(5,F6))*Hypothèses!$D$7) -> 116100 | G7: =IF(G6=0,0,Hypothèses!$C$7*1000000*INDEX(Hypothèses!$C$16:$G$16,1,MIN(5,G6))*Hypothèses!$D$7) -> 167700
A8: Cotisations annuelles (= pots versés) | B8: M F | C8: =C7*Hypothèses!$E$7*12 -> 1161000000 | D8: =D7*Hypothèses!$E$7*12 -> 4450500000 | E8: =E7*Hypothèses!$E$7*12 -> 10642500000 | F8: =F7*Hypothèses!$E$7*12 -> 17415000000 | G8: =G7*Hypothèses!$E$7*12 -> 25155000000
A9: Pays ouvert (1/0) | C9: =IF(C6>0,1,0) -> 1 | D9: =IF(D6>0,1,0) -> 1 | E9: =IF(E6>0,1,0) -> 1 | F9: =IF(F6>0,1,0) -> 1 | G9: =IF(G6>0,1,0) -> 1
A10: Côte d'Ivoire
A11: Ancienneté (années) | C11: =MAX(0,2027-Hypothèses!$B$8+1) -> 0 | D11: =MAX(0,2028-Hypothèses!$B$8+1) -> 0 | E11: =MAX(0,2029-Hypothèses!$B$8+1) -> 1 | F11: =MAX(0,2030-Hypothèses!$B$8+1) -> 2 | G11: =MAX(0,2031-Hypothèses!$B$8+1) -> 3
A12: Membres actifs | B12: membres | C12: =IF(C11=0,0,Hypothèses!$C$8*1000000*INDEX(Hypothèses!$C$16:$G$16,1,MIN(5,C11))*Hypothèses!$D$8) -> 0 | D12: =IF(D11=0,0,Hypothèses!$C$8*1000000*INDEX(Hypothèses!$C$16:$G$16,1,MIN(5,D11))*Hypothèses!$D$8) -> 0 | E12: =IF(E11=0,0,Hypothèses!$C$8*1000000*INDEX(Hypothèses!$C$16:$G$16,1,MIN(5,E11))*Hypothèses!$D$8) -> 7560 | F12: =IF(F11=0,0,Hypothèses!$C$8*1000000*INDEX(Hypothèses!$C$16:$G$16,1,MIN(5,F11))*Hypothèses!$D$8) -> 28980 | G12: =IF(G11=0,0,Hypothèses!$C$8*1000000*INDEX(Hypothèses!$C$16:$G$16,1,MIN(5,G11))*Hypothèses!$D$8) -> 69300
A13: Cotisations annuelles (= pots versés) | B13: M F | C13: =C12*Hypothèses!$E$8*12 -> 0 | D13: =D12*Hypothèses!$E$8*12 -> 0 | E13: =E12*Hypothèses!$E$8*12 -> 1814400000 | F13: =F12*Hypothèses!$E$8*12 -> 6955200000 | G13: =G12*Hypothèses!$E$8*12 -> 16632000000
A14: Pays ouvert (1/0) | C14: =IF(C11>0,1,0) -> 0 | D14: =IF(D11>0,1,0) -> 0 | E14: =IF(E11>0,1,0) -> 1 | F14: =IF(F11>0,1,0) -> 1 | G14: =IF(G11>0,1,0) -> 1
A15: Mali
A16: Ancienneté (années) | C16: =MAX(0,2027-Hypothèses!$B$9+1) -> 0 | D16: =MAX(0,2028-Hypothèses!$B$9+1) -> 0 | E16: =MAX(0,2029-Hypothèses!$B$9+1) -> 0 | F16: =MAX(0,2030-Hypothèses!$B$9+1) -> 1 | G16: =MAX(0,2031-Hypothèses!$B$9+1) -> 2
A17: Membres actifs | B17: membres | C17: =IF(C16=0,0,Hypothèses!$C$9*1000000*INDEX(Hypothèses!$C$16:$G$16,1,MIN(5,C16))*Hypothèses!$D$9) -> 0 | D17: =IF(D16=0,0,Hypothèses!$C$9*1000000*INDEX(Hypothèses!$C$16:$G$16,1,MIN(5,D16))*Hypothèses!$D$9) -> 0 | E17: =IF(E16=0,0,Hypothèses!$C$9*1000000*INDEX(Hypothèses!$C$16:$G$16,1,MIN(5,E16))*Hypothèses!$D$9) -> 0 | F17: =IF(F16=0,0,Hypothèses!$C$9*1000000*INDEX(Hypothèses!$C$16:$G$16,1,MIN(5,F16))*Hypothèses!$D$9) -> 5040 | G17: =IF(G16=0,0,Hypothèses!$C$9*1000000*INDEX(Hypothèses!$C$16:$G$16,1,MIN(5,G16))*Hypothèses!$D$9) -> 19320
A18: Cotisations annuelles (= pots versés) | B18: M F | C18: =C17*Hypothèses!$E$9*12 -> 0 | D18: =D17*Hypothèses!$E$9*12 -> 0 | E18: =E17*Hypothèses!$E$9*12 -> 0 | F18: =F17*Hypothèses!$E$9*12 -> 756000000 | G18: =G17*Hypothèses!$E$9*12 -> 2898000000
A19: Pays ouvert (1/0) | C19: =IF(C16>0,1,0) -> 0 | D19: =IF(D16>0,1,0) -> 0 | E19: =IF(E16>0,1,0) -> 0 | F19: =IF(F16>0,1,0) -> 1 | G19: =IF(G16>0,1,0) -> 1
A20: Niger
A21: Ancienneté (années) | C21: =MAX(0,2027-Hypothèses!$B$10+1) -> 0 | D21: =MAX(0,2028-Hypothèses!$B$10+1) -> 0 | E21: =MAX(0,2029-Hypothèses!$B$10+1) -> 0 | F21: =MAX(0,2030-Hypothèses!$B$10+1) -> 0 | G21: =MAX(0,2031-Hypothèses!$B$10+1) -> 1
A22: Membres actifs | B22: membres | C22: =IF(C21=0,0,Hypothèses!$C$10*1000000*INDEX(Hypothèses!$C$16:$G$16,1,MIN(5,C21))*Hypothèses!$D$10) -> 0 | D22: =IF(D21=0,0,Hypothèses!$C$10*1000000*INDEX(Hypothèses!$C$16:$G$16,1,MIN(5,D21))*Hypothèses!$D$10) -> 0 | E22: =IF(E21=0,0,Hypothèses!$C$10*1000000*INDEX(Hypothèses!$C$16:$G$16,1,MIN(5,E21))*Hypothèses!$D$10) -> 0 | F22: =IF(F21=0,0,Hypothèses!$C$10*1000000*INDEX(Hypothèses!$C$16:$G$16,1,MIN(5,F21))*Hypothèses!$D$10) -> 0 | G22: =IF(G21=0,0,Hypothèses!$C$10*1000000*INDEX(Hypothèses!$C$16:$G$16,1,MIN(5,G21))*Hypothèses!$D$10) -> 4500
A23: Cotisations annuelles (= pots versés) | B23: M F | C23: =C22*Hypothèses!$E$10*12 -> 0 | D23: =D22*Hypothèses!$E$10*12 -> 0 | E23: =E22*Hypothèses!$E$10*12 -> 0 | F23: =F22*Hypothèses!$E$10*12 -> 0 | G23: =G22*Hypothèses!$E$10*12 -> 540000000
A24: Pays ouvert (1/0) | C24: =IF(C21>0,1,0) -> 0 | D24: =IF(D21>0,1,0) -> 0 | E24: =IF(E21>0,1,0) -> 0 | F24: =IF(F21>0,1,0) -> 0 | G24: =IF(G21>0,1,0) -> 1
A25: Sénégal
A26: Ancienneté (années) | C26: =MAX(0,2027-Hypothèses!$B$11+1) -> 0 | D26: =MAX(0,2028-Hypothèses!$B$11+1) -> 0 | E26: =MAX(0,2029-Hypothèses!$B$11+1) -> 0 | F26: =MAX(0,2030-Hypothèses!$B$11+1) -> 0 | G26: =MAX(0,2031-Hypothèses!$B$11+1) -> 1
A27: Membres actifs | B27: membres | C27: =IF(C26=0,0,Hypothèses!$C$11*1000000*INDEX(Hypothèses!$C$16:$G$16,1,MIN(5,C26))*Hypothèses!$D$11) -> 0 | D27: =IF(D26=0,0,Hypothèses!$C$11*1000000*INDEX(Hypothèses!$C$16:$G$16,1,MIN(5,D26))*Hypothèses!$D$11) -> 0 | E27: =IF(E26=0,0,Hypothèses!$C$11*1000000*INDEX(Hypothèses!$C$16:$G$16,1,MIN(5,E26))*Hypothèses!$D$11) -> 0 | F27: =IF(F26=0,0,Hypothèses!$C$11*1000000*INDEX(Hypothèses!$C$16:$G$16,1,MIN(5,F26))*Hypothèses!$D$11) -> 0 | G27: =IF(G26=0,0,Hypothèses!$C$11*1000000*INDEX(Hypothèses!$C$16:$G$16,1,MIN(5,G26))*Hypothèses!$D$11) -> 3150
A28: Cotisations annuelles (= pots versés) | B28: M F | C28: =C27*Hypothèses!$E$11*12 -> 0 | D28: =D27*Hypothèses!$E$11*12 -> 0 | E28: =E27*Hypothèses!$E$11*12 -> 0 | F28: =F27*Hypothèses!$E$11*12 -> 0 | G28: =G27*Hypothèses!$E$11*12 -> 756000000
A29: Pays ouvert (1/0) | C29: =IF(C26>0,1,0) -> 0 | D29: =IF(D26>0,1,0) -> 0 | E29: =IF(E26>0,1,0) -> 0 | F29: =IF(F26>0,1,0) -> 0 | G29: =IF(G26>0,1,0) -> 1
A30: Bénin / Togo
A31: Ancienneté (années) | C31: =MAX(0,2027-Hypothèses!$B$12+1) -> 0 | D31: =MAX(0,2028-Hypothèses!$B$12+1) -> 0 | E31: =MAX(0,2029-Hypothèses!$B$12+1) -> 0 | F31: =MAX(0,2030-Hypothèses!$B$12+1) -> 0 | G31: =MAX(0,2031-Hypothèses!$B$12+1) -> 0
A32: Membres actifs | B32: membres | C32: =IF(C31=0,0,Hypothèses!$C$12*1000000*INDEX(Hypothèses!$C$16:$G$16,1,MIN(5,C31))*Hypothèses!$D$12) -> 0 | D32: =IF(D31=0,0,Hypothèses!$C$12*1000000*INDEX(Hypothèses!$C$16:$G$16,1,MIN(5,D31))*Hypothèses!$D$12) -> 0 | E32: =IF(E31=0,0,Hypothèses!$C$12*1000000*INDEX(Hypothèses!$C$16:$G$16,1,MIN(5,E31))*Hypothèses!$D$12) -> 0 | F32: =IF(F31=0,0,Hypothèses!$C$12*1000000*INDEX(Hypothèses!$C$16:$G$16,1,MIN(5,F31))*Hypothèses!$D$12) -> 0 | G32: =IF(G31=0,0,Hypothèses!$C$12*1000000*INDEX(Hypothèses!$C$16:$G$16,1,MIN(5,G31))*Hypothèses!$D$12) -> 0
A33: Cotisations annuelles (= pots versés) | B33: M F | C33: =C32*Hypothèses!$E$12*12 -> 0 | D33: =D32*Hypothèses!$E$12*12 -> 0 | E33: =E32*Hypothèses!$E$12*12 -> 0 | F33: =F32*Hypothèses!$E$12*12 -> 0 | G33: =G32*Hypothèses!$E$12*12 -> 0
A34: Pays ouvert (1/0) | C34: =IF(C31>0,1,0) -> 0 | D34: =IF(D31>0,1,0) -> 0 | E34: =IF(E31>0,1,0) -> 0 | F34: =IF(F31>0,1,0) -> 0 | G34: =IF(G31>0,1,0) -> 0
A35: Total
A36: Membres actifs B2C | B36: membres | C36: =C7+C12+C17+C22+C27+C32 -> 7740 | D36: =D7+D12+D17+D22+D27+D32 -> 29670 | E36: =E7+E12+E17+E22+E27+E32 -> 78510 | F36: =F7+F12+F17+F22+F27+F32 -> 150120 | G36: =G7+G12+G17+G22+G27+G32 -> 263970
A37: Nouveaux membres B2C | B37: membres | C37: =C36 -> 7740 | D37: =MAX(0,D36-C36) -> 21930 | E37: =MAX(0,E36-D36) -> 48840 | F37: =MAX(0,F36-E36) -> 71610 | G37: =MAX(0,G36-F36) -> 113850
A38: Cotisations B2C (= pots versés) | B38: M F | C38: =C8+C13+C18+C23+C28+C33 -> 1161000000 | D38: =D8+D13+D18+D23+D28+D33 -> 4450500000 | E38: =E8+E13+E18+E23+E28+E33 -> 12456900000 | F38: =F8+F13+F18+F23+F28+F33 -> 25126200000 | G38: =G8+G13+G18+G23+G28+G33 -> 45981000000
A39: Pays ouverts | B39: pays | C39: =C9+C14+C19+C24+C29+C34 -> 1 | D39: =D9+D14+D19+D24+D29+D34 -> 1 | E39: =E9+E14+E19+E24+E29+E34 -> 2 | F39: =F9+F14+F19+F24+F29+F34 -> 3 | G39: =G9+G14+G19+G24+G29+G34 -> 5
A40: Membres SFD (potentiel B2B) | B40: membres | C40: =Hypothèses!C$19 -> 5000 | D40: =Hypothèses!D$19 -> 30000 | E40: =Hypothèses!E$19 -> 80000 | F40: =Hypothèses!F$19 -> 150000 | G40: =Hypothèses!G$19 -> 250000
A41: Nouveaux membres SFD | B41: membres | C41: =C40 -> 5000 | D41: =MAX(0,D40-C40) -> 25000 | E41: =MAX(0,E40-D40) -> 50000 | F41: =MAX(0,F40-E40) -> 70000 | G41: =MAX(0,G40-F40) -> 100000

Sheet Modèles
A1: Smart Tontine — Compte de résultat de chaque modèle
A2: Montants en millions de FCFA · mêmes marchés, mêmes coûts : seuls les paramètres de la matrice (Hypothèses §4) changent
A4: Indicateur | B4: Unité | C4: 2027 | D4: 2028 | E4: 2029 | F4: 2030 | G4: 2031 | H4: Méthode
A5: Modèle A — Commission seule
A6: Membres actifs B2C | B6: membres | C6: =Déploiement!C$36*Hypothèses!$C$58 -> 7740 | D6: =Déploiement!D$36*Hypothèses!$C$58 -> 29670 | E6: =Déploiement!E$36*Hypothèses!$C$58 -> 78510 | F6: =Déploiement!F$36*Hypothèses!$C$58 -> 150120 | G6: =Déploiement!G$36*Hypothèses!$C$58 -> 263970
A7: Membres SFD gérés (B2B) | B7: membres | C7: =Déploiement!C$40*Hypothèses!$C$67 -> 0 | D7: =Déploiement!D$40*Hypothèses!$C$67 -> 0 | E7: =Déploiement!E$40*Hypothèses!$C$67 -> 0 | F7: =Déploiement!F$40*Hypothèses!$C$67 -> 0 | G7: =Déploiement!G$40*Hypothèses!$C$67 -> 0
A8: Cotisations B2C (= pots versés) | B8: M F | C8: =Déploiement!C$38*Hypothèses!$C$58 -> 1161000000 | D8: =Déploiement!D$38*Hypothèses!$C$58 -> 4450500000 | E8: =Déploiement!E$38*Hypothèses!$C$58 -> 12456900000 | F8: =Déploiement!F$38*Hypothèses!$C$58 -> 25126200000 | G8: =Déploiement!G$38*Hypothèses!$C$58 -> 45981000000
A9: Pots retirés vers Mobile Money | B9: M F | C9: =C8*(1-MIN(0.9,Hypothèses!C$17+Hypothèses!$C$71)) -> 986850000 | D9: =D8*(1-MIN(0.9,Hypothèses!D$17+Hypothèses!$C$71)) -> 3337875000 | E9: =E8*(1-MIN(0.9,Hypothèses!E$17+Hypothèses!$C$71)) -> 8719830000 | F9: =F8*(1-MIN(0.9,Hypothèses!F$17+Hypothèses!$C$71)) -> 16332030000 | G9: =G8*(1-MIN(0.9,Hypothèses!G$17+Hypothèses!$C$71)) -> 27588600000 | H9: cotisations × (1 − recirculation) : ce qui entre par Mobile Money finit par ressortir
A10: Crédits versés (via SFD) | B10: M F | C10: =C6*Hypothèses!C$18*Hypothèses!$C$35*Hypothèses!$C$65 -> 0 | D10: =D6*Hypothèses!D$18*Hypothèses!$C$35*Hypothèses!$C$65 -> 0 | E10: =E6*Hypothèses!E$18*Hypothèses!$C$35*Hypothèses!$C$65 -> 0 | F10: =F6*Hypothèses!F$18*Hypothèses!$C$35*Hypothèses!$C$65 -> 0 | G10: =G6*Hypothèses!G$18*Hypothèses!$C$35*Hypothèses!$C$65 -> 0
A11: Revenus
A12: Commission sur les pots | B12: M F | C12: =C8*Hypothèses!$C$59 -> 11610000 | D12: =D8*Hypothèses!$C$59 -> 44505000 | E12: =E8*Hypothèses!$C$59 -> 124569000 | F12: =F8*Hypothèses!$C$59 -> 251262000 | G12: =G8*Hypothèses!$C$59 -> 459810000
A13: Frais de retrait | B13: M F | C13: =C9*Hypothèses!$C$60 -> 0 | D13: =D9*Hypothèses!$C$60 -> 0 | E13: =E9*Hypothèses!$C$60 -> 0 | F13: =F9*Hypothèses!$C$60 -> 0 | G13: =G9*Hypothèses!$C$60 -> 0
A14: Abonnements Organisateur Pro | B14: M F | C14: =C6/Hypothèses!$C$30*Hypothèses!$C$62*Hypothèses!$C$31*12 -> 0 | D14: =D6/Hypothèses!$C$30*Hypothèses!$C$62*Hypothèses!$C$31*12 -> 0 | E14: =E6/Hypothèses!$C$30*Hypothèses!$C$62*Hypothèses!$C$31*12 -> 0 | F14: =F6/Hypothèses!$C$30*Hypothèses!$C$62*Hypothèses!$C$31*12 -> 0 | G14: =G6/Hypothèses!$C$30*Hypothèses!$C$62*Hypothèses!$C$31*12 -> 0 | H14: groupes × conversion × prix × 12
A15: Abonnements Smart Tontine+ | B15: M F | C15: =C6*Hypothèses!$C$63*Hypothèses!$C$32*12 -> 0 | D15: =D6*Hypothèses!$C$63*Hypothèses!$C$32*12 -> 0 | E15: =E6*Hypothèses!$C$63*Hypothèses!$C$32*12 -> 0 | F15: =F6*Hypothèses!$C$63*Hypothèses!$C$32*12 -> 0 | G15: =G6*Hypothèses!$C$63*Hypothèses!$C$32*12 -> 0
A16: Revenus du float | B16: M F | C16: =C6*Hypothèses!$C$33*Hypothèses!$C$34*Hypothèses!$C$64 -> 1857600 | D16: =D6*Hypothèses!$C$33*Hypothèses!$C$34*Hypothèses!$C$64 -> 7120800 | E16: =E6*Hypothèses!$C$33*Hypothèses!$C$34*Hypothèses!$C$64 -> 18842400 | F16: =F6*Hypothèses!$C$33*Hypothèses!$C$34*Hypothèses!$C$64 -> 36028800 | G16: =G6*Hypothèses!$C$33*Hypothèses!$C$34*Hypothèses!$C$64 -> 63352800
A17: Part des intérêts de crédit | B17: M F | C17: =C10*Hypothèses!$C$36*Hypothèses!$C$37 -> 0 | D17: =D10*Hypothèses!$C$36*Hypothèses!$C$37 -> 0 | E17: =E10*Hypothèses!$C$36*Hypothèses!$C$37 -> 0 | F17: =F10*Hypothèses!$C$36*Hypothèses!$C$37 -> 0 | G17: =G10*Hypothèses!$C$36*Hypothèses!$C$37 -> 0
A18: Commissions d'assurance | B18: M F | C18: =C6*Hypothèses!$C$41*Hypothèses!$C$42*Hypothèses!$C$43*Hypothèses!$C$66 -> 0 | D18: =D6*Hypothèses!$C$41*Hypothèses!$C$42*Hypothèses!$C$43*Hypothèses!$C$66 -> 0 | E18: =E6*Hypothèses!$C$41*Hypothèses!$C$42*Hypothèses!$C$43*Hypothèses!$C$66 -> 0 | F18: =F6*Hypothèses!$C$41*Hypothèses!$C$42*Hypothèses!$C$43*Hypothèses!$C$66 -> 0 | G18: =G6*Hypothèses!$C$41*Hypothèses!$C$42*Hypothèses!$C$43*Hypothèses!$C$66 -> 0
A19: Licences SFD | B19: M F | C19: =C7*Hypothèses!$C$44*12 -> 0 | D19: =D7*Hypothèses!$C$44*12 -> 0 | E19: =E7*Hypothèses!$C$44*12 -> 0 | F19: =F7*Hypothèses!$C$44*12 -> 0 | G19: =G7*Hypothèses!$C$44*12 -> 0
A20: Frais d'apport de crédit (SFD) | B20: M F | C20: =C7*Hypothèses!C$18*Hypothèses!$C$35*Hypothèses!$C$40 -> 0 | D20: =D7*Hypothèses!D$18*Hypothèses!$C$35*Hypothèses!$C$40 -> 0 | E20: =E7*Hypothèses!E$18*Hypothèses!$C$35*Hypothèses!$C$40 -> 0 | F20: =F7*Hypothèses!F$18*Hypothèses!$C$35*Hypothèses!$C$40 -> 0 | G20: =G7*Hypothèses!G$18*Hypothèses!$C$35*Hypothèses!$C$40 -> 0
A21: Chiffre d'affaires | B21: M F | C21: =SUM(C12:C20) -> 13467600 | D21: =SUM(D12:D20) -> 51625800 | E21: =SUM(E12:E20) -> 143411400 | F21: =SUM(F12:F20) -> 287290800 | G21: =SUM(G12:G20) -> 523162800
A22: Coûts variables
A23: Frais Mobile Money (entrée + sortie) | B23: M F | C23: =C9*(Hypothèses!$C$24+Hypothèses!$C$25)*(1-Hypothèses!$C$61)*(1-Hypothèses!$C$70) -> 14802750 | D23: =D9*(Hypothèses!$C$24+Hypothèses!$C$25)*(1-Hypothèses!$C$61)*(1-Hypothèses!$C$70) -> 50068125 | E23: =E9*(Hypothèses!$C$24+Hypothèses!$C$25)*(1-Hypothèses!$C$61)*(1-Hypothèses!$C$70) -> 130797450 | F23: =F9*(Hypothèses!$C$24+Hypothèses!$C$25)*(1-Hypothèses!$C$61)*(1-Hypothèses!$C$70) -> 244980450 | G23: =G9*(Hypothèses!$C$24+Hypothèses!$C$25)*(1-Hypothèses!$C$61)*(1-Hypothèses!$C$70) -> 413829000 | H23: seul l'argent qui entre et ressort par Mobile Money coûte des frais
A24: SMS, hébergement | B24: M F | C24: =(C6+0.5*C7)*(Hypothèses!$C$26+Hypothèses!$C$27) -> 2089800 | D24: =(D6+0.5*D7)*(Hypothèses!$C$26+Hypothèses!$C$27) -> 8010900 | E24: =(E6+0.5*E7)*(Hypothèses!$C$26+Hypothèses!$C$27) -> 21197700 | F24: =(F6+0.5*F7)*(Hypothèses!$C$26+Hypothèses!$C$27) -> 40532400 | G24: =(G6+0.5*G7)*(Hypothèses!$C$26+Hypothèses!$C$27) -> 71271900 | H24: membres SFD comptés à 50 %
A25: KYC | B25: M F | C25: =C6*Hypothèses!$C$29*Hypothèses!$C$28 -> 967500 | D25: =MAX(0,D6-C6)*Hypothèses!$C$29*Hypothèses!$C$28 -> 2741250 | E25: =MAX(0,E6-D6)*Hypothèses!$C$29*Hypothèses!$C$28 -> 6105000 | F25: =MAX(0,F6-E6)*Hypothèses!$C$29*Hypothèses!$C$28 -> 8951250 | G25: =MAX(0,G6-F6)*Hypothèses!$C$29*Hypothèses!$C$28 -> 14231250
A26: Garantie de première perte (crédit) | B26: M F | C26: =C10*Hypothèses!$C$38*Hypothèses!$C$39 -> 0 | D26: =D10*Hypothèses!$C$38*Hypothèses!$C$39 -> 0 | E26: =E10*Hypothèses!$C$38*Hypothèses!$C$39 -> 0 | F26: =F10*Hypothèses!$C$38*Hypothèses!$C$39 -> 0 | G26: =G10*Hypothèses!$C$38*Hypothèses!$C$39 -> 0
A27: Acquisition | B27: M F | C27: =C6*Hypothèses!$C$68+C7*Hypothèses!$C$69 -> 9288000 | D27: =MAX(0,D6-C6)*Hypothèses!$C$68+MAX(0,D7-C7)*Hypothèses!$C$69 -> 26316000 | E27: =MAX(0,E6-D6)*Hypothèses!$C$68+MAX(0,E7-D7)*Hypothèses!$C$69 -> 58608000 | F27: =MAX(0,F6-E6)*Hypothèses!$C$68+MAX(0,F7-E7)*Hypothèses!$C$69 -> 85932000 | G27: =MAX(0,G6-F6)*Hypothèses!$C$68+MAX(0,G7-F7)*Hypothèses!$C$69 -> 136620000 | H27: nouveaux membres × CAC
A28: Total coûts variables | B28: M F | C28: =SUM(C23:C27) -> 27148050 | D28: =SUM(D23:D27) -> 87136275 | E28: =SUM(E23:E27) -> 216708150 | F28: =SUM(F23:F27) -> 380396100 | G28: =SUM(G23:G27) -> 635952150
A29: Marge sur coûts variables | B29: M F | C29: =C21-C28 -> -13680450 | D29: =D21-D28 -> -35510475 | E29: =E21-E28 -> -73296750 | F29: =F21-F28 -> -93105300 | G29: =G21-G28 -> -112789350
A30: Coûts fixes
A31: Siège (équipe + charges fixes) | B31: M F | C31: =(Hypothèses!C$20*Hypothèses!$C$46+Hypothèses!$C$49)*(1-Hypothèses!$C$72) -> 88000000 | D31: =(Hypothèses!D$20*Hypothèses!$C$46+Hypothèses!$C$49)*(1-Hypothèses!$C$72) -> 112000000 | E31: =(Hypothèses!E$20*Hypothèses!$C$46+Hypothèses!$C$49)*(1-Hypothèses!$C$72) -> 136000000 | F31: =(Hypothèses!F$20*Hypothèses!$C$46+Hypothèses!$C$49)*(1-Hypothèses!$C$72) -> 160000000 | G31: =(Hypothèses!G$20*Hypothèses!$C$46+Hypothèses!$C$49)*(1-Hypothèses!$C$72) -> 184000000
A32: Pays ouverts (équipes + marque) | B32: M F | C32: =Déploiement!C$39*(Hypothèses!$C$47+Hypothèses!$C$48)*Hypothèses!$C$58+Déploiement!C$39*Hypothèses!$C$47*0.5*(1-Hypothèses!$C$58) -> 57000000 | D32: =Déploiement!D$39*(Hypothèses!$C$47+Hypothèses!$C$48)*Hypothèses!$C$58+Déploiement!D$39*Hypothèses!$C$47*0.5*(1-Hypothèses!$C$58) -> 57000000 | E32: =Déploiement!E$39*(Hypothèses!$C$47+Hypothèses!$C$48)*Hypothèses!$C$58+Déploiement!E$39*Hypothèses!$C$47*0.5*(1-Hypothèses!$C$58) -> 114000000 | F32: =Déploiement!F$39*(Hypothèses!$C$47+Hypothèses!$C$48)*Hypothèses!$C$58+Déploiement!F$39*Hypothèses!$C$47*0.5*(1-Hypothèses!$C$58) -> 171000000 | G32: =Déploiement!G$39*(Hypothèses!$C$47+Hypothèses!$C$48)*Hypothèses!$C$58+Déploiement!G$39*Hypothèses!$C$47*0.5*(1-Hypothèses!$C$58) -> 285000000 | H32: B2C : coût pays complet ; modèle E (sans B2C) : demi-coût, pas de marque
A33: Équipes crédit / B2B | B33: M F | C33: =Hypothèses!$C$50*Hypothèses!C$21*Hypothèses!$C$65+Hypothèses!$C$51*IF(Hypothèses!$C$67>0,1,0) -> 0 | D33: =Hypothèses!$C$50*Hypothèses!D$21*Hypothèses!$C$65+Hypothèses!$C$51*IF(Hypothèses!$C$67>0,1,0) -> 0 | E33: =Hypothèses!$C$50*Hypothèses!E$21*Hypothèses!$C$65+Hypothèses!$C$51*IF(Hypothèses!$C$67>0,1,0) -> 0 | F33: =Hypothèses!$C$50*Hypothèses!F$21*Hypothèses!$C$65+Hypothèses!$C$51*IF(Hypothèses!$C$67>0,1,0) -> 0 | G33: =Hypothèses!$C$50*Hypothèses!G$21*Hypothèses!$C$65+Hypothèses!$C$51*IF(Hypothèses!$C$67>0,1,0) -> 0
A34: Total coûts fixes | B34: M F | C34: =SUM(C31:C33) -> 145000000 | D34: =SUM(D31:D33) -> 169000000 | E34: =SUM(E31:E33) -> 250000000 | F34: =SUM(F31:F33) -> 331000000 | G34: =SUM(G31:G33) -> 469000000
A35: Résultat et trésorerie
A36: EBITDA | B36: M F | C36: =C29-C34 -> -158680450 | D36: =D29-D34 -> -204510475 | E36: =E29-E34 -> -323296750 | F36: =F29-F34 -> -424105300 | G36: =G29-G34 -> -581789350
A37: Impôt (sur EBITDA − amortissement si positif) | B37: M F | C37: =MAX(0,C36-Hypothèses!$C$52/3*IF(0<3,1,0))*Hypothèses!$C$53 -> 0 | D37: =MAX(0,D36-Hypothèses!$C$52/3*IF(1<3,1,0))*Hypothèses!$C$53 -> 0 | E37: =MAX(0,E36-Hypothèses!$C$52/3*IF(2<3,1,0))*Hypothèses!$C$53 -> 0 | F37: =MAX(0,F36-Hypothèses!$C$52/3*IF(3<3,1,0))*Hypothèses!$C$53 -> 0 | G37: =MAX(0,G36-Hypothèses!$C$52/3*IF(4<3,1,0))*Hypothèses!$C$53 -> 0
A38: Flux de trésorerie | B38: M F | C38: =C36-C37-IF(0=0,Hypothèses!$C$52,0) -> -203680450 | D38: =D36-D37-IF(1=0,Hypothèses!$C$52,0) -> -204510475 | E38: =E36-E37-IF(2=0,Hypothèses!$C$52,0) -> -323296750 | F38: =F36-F37-IF(3=0,Hypothèses!$C$52,0) -> -424105300 | G38: =G36-G37-IF(4=0,Hypothèses!$C$52,0) -> -581789350
A39: Trésorerie cumulée | B39: M F | C39: =C38 -> -203680450 | D39: =C39+D38 -> -408190925 | E39: =D39+E38 -> -731487675 | F39: =E39+F38 -> -1155592975 | G39: =F39+G38 -> -1737382325
A40: EBITDA positif (1 = oui) | B40: indicateur | C40: =IF(C36>0,1,0) -> 0 | D40: =IF(D36>0,1,0) -> 0 | E40: =IF(E36>0,1,0) -> 0 | F40: =IF(F36>0,1,0) -> 0 | G40: =IF(G36>0,1,0) -> 0
A41: Marge sur coûts variables par membre (hors acquisition) | B41: F | C41: =IF((C6+C7)=0,0,(C29+C27)/(C6+C7)) -> -567.5 | D41: =IF((D6+D7)=0,0,(D29+D27)/(D6+D7)) -> -309.8913 | E41: =IF((E6+E7)=0,0,(E29+E27)/(E6+E7)) -> -187.094 | F41: =IF((F6+F7)=0,0,(F29+F27)/(F6+F7)) -> -47.783773 | G41: =IF((G6+G7)=0,0,(G29+G27)/(G6+G7)) -> 90.277872 | H41: par membre (B2C + B2B) et par an
A43: Modèle B — Transactionnel
A44: Membres actifs B2C | B44: membres | C44: =Déploiement!C$36*Hypothèses!$D$58 -> 7740 | D44: =Déploiement!D$36*Hypothèses!$D$58 -> 29670 | E44: =Déploiement!E$36*Hypothèses!$D$58 -> 78510 | F44: =Déploiement!F$36*Hypothèses!$D$58 -> 150120 | G44: =Déploiement!G$36*Hypothèses!$D$58 -> 263970
A45: Membres SFD gérés (B2B) | B45: membres | C45: =Déploiement!C$40*Hypothèses!$D$67 -> 0 | D45: =Déploiement!D$40*Hypothèses!$D$67 -> 0 | E45: =Déploiement!E$40*Hypothèses!$D$67 -> 0 | F45: =Déploiement!F$40*Hypothèses!$D$67 -> 0 | G45: =Déploiement!G$40*Hypothèses!$D$67 -> 0
A46: Cotisations B2C (= pots versés) | B46: M F | C46: =Déploiement!C$38*Hypothèses!$D$58 -> 1161000000 | D46: =Déploiement!D$38*Hypothèses!$D$58 -> 4450500000 | E46: =Déploiement!E$38*Hypothèses!$D$58 -> 12456900000 | F46: =Déploiement!F$38*Hypothèses!$D$58 -> 25126200000 | G46: =Déploiement!G$38*Hypothèses!$D$58 -> 45981000000
A47: Pots retirés vers Mobile Money | B47: M F | C47: =C46*(1-MIN(0.9,Hypothèses!C$17+Hypothèses!$D$71)) -> 986850000 | D47: =D46*(1-MIN(0.9,Hypothèses!D$17+Hypothèses!$D$71)) -> 3337875000 | E47: =E46*(1-MIN(0.9,Hypothèses!E$17+Hypothèses!$D$71)) -> 8719830000 | F47: =F46*(1-MIN(0.9,Hypothèses!F$17+Hypothèses!$D$71)) -> 16332030000 | G47: =G46*(1-MIN(0.9,Hypothèses!G$17+Hypothèses!$D$71)) -> 27588600000 | H47: cotisations × (1 − recirculation) : ce qui entre par Mobile Money finit par ressortir
A48: Crédits versés (via SFD) | B48: M F | C48: =C44*Hypothèses!C$18*Hypothèses!$C$35*Hypothèses!$D$65 -> 0 | D48: =D44*Hypothèses!D$18*Hypothèses!$C$35*Hypothèses!$D$65 -> 0 | E48: =E44*Hypothèses!E$18*Hypothèses!$C$35*Hypothèses!$D$65 -> 0 | F48: =F44*Hypothèses!F$18*Hypothèses!$C$35*Hypothèses!$D$65 -> 0 | G48: =G44*Hypothèses!G$18*Hypothèses!$C$35*Hypothèses!$D$65 -> 0
A49: Revenus
A50: Commission sur les pots | B50: M F | C50: =C46*Hypothèses!$D$59 -> 11610000 | D50: =D46*Hypothèses!$D$59 -> 44505000 | E50: =E46*Hypothèses!$D$59 -> 124569000 | F50: =F46*Hypothèses!$D$59 -> 251262000 | G50: =G46*Hypothèses!$D$59 -> 459810000
A51: Frais de retrait | B51: M F | C51: =C47*Hypothèses!$D$60 -> 9868500 | D51: =D47*Hypothèses!$D$60 -> 33378750 | E51: =E47*Hypothèses!$D$60 -> 87198300 | F51: =F47*Hypothèses!$D$60 -> 163320300 | G51: =G47*Hypothèses!$D$60 -> 275886000
A52: Abonnements Organisateur Pro | B52: M F | C52: =C44/Hypothèses!$C$30*Hypothèses!$D$62*Hypothèses!$C$31*12 -> 0 | D52: =D44/Hypothèses!$C$30*Hypothèses!$D$62*Hypothèses!$C$31*12 -> 0 | E52: =E44/Hypothèses!$C$30*Hypothèses!$D$62*Hypothèses!$C$31*12 -> 0 | F52: =F44/Hypothèses!$C$30*Hypothèses!$D$62*Hypothèses!$C$31*12 -> 0 | G52: =G44/Hypothèses!$C$30*Hypothèses!$D$62*Hypothèses!$C$31*12 -> 0 | H52: groupes × conversion × prix × 12
A53: Abonnements Smart Tontine+ | B53: M F | C53: =C44*Hypothèses!$D$63*Hypothèses!$C$32*12 -> 0 | D53: =D44*Hypothèses!$D$63*Hypothèses!$C$32*12 -> 0 | E53: =E44*Hypothèses!$D$63*Hypothèses!$C$32*12 -> 0 | F53: =F44*Hypothèses!$D$63*Hypothèses!$C$32*12 -> 0 | G53: =G44*Hypothèses!$D$63*Hypothèses!$C$32*12 -> 0
A54: Revenus du float | B54: M F | C54: =C44*Hypothèses!$C$33*Hypothèses!$C$34*Hypothèses!$D$64 -> 1857600 | D54: =D44*Hypothèses!$C$33*Hypothèses!$C$34*Hypothèses!$D$64 -> 7120800 | E54: =E44*Hypothèses!$C$33*Hypothèses!$C$34*Hypothèses!$D$64 -> 18842400 | F54: =F44*Hypothèses!$C$33*Hypothèses!$C$34*Hypothèses!$D$64 -> 36028800 | G54: =G44*Hypothèses!$C$33*Hypothèses!$C$34*Hypothèses!$D$64 -> 63352800
A55: Part des intérêts de crédit | B55: M F | C55: =C48*Hypothèses!$C$36*Hypothèses!$C$37 -> 0 | D55: =D48*Hypothèses!$C$36*Hypothèses!$C$37 -> 0 | E55: =E48*Hypothèses!$C$36*Hypothèses!$C$37 -> 0 | F55: =F48*Hypothèses!$C$36*Hypothèses!$C$37 -> 0 | G55: =G48*Hypothèses!$C$36*Hypothèses!$C$37 -> 0
A56: Commissions d'assurance | B56: M F | C56: =C44*Hypothèses!$C$41*Hypothèses!$C$42*Hypothèses!$C$43*Hypothèses!$D$66 -> 0 | D56: =D44*Hypothèses!$C$41*Hypothèses!$C$42*Hypothèses!$C$43*Hypothèses!$D$66 -> 0 | E56: =E44*Hypothèses!$C$41*Hypothèses!$C$42*Hypothèses!$C$43*Hypothèses!$D$66 -> 0 | F56: =F44*Hypothèses!$C$41*Hypothèses!$C$42*Hypothèses!$C$43*Hypothèses!$D$66 -> 0 | G56: =G44*Hypothèses!$C$41*Hypothèses!$C$42*Hypothèses!$C$43*Hypothèses!$D$66 -> 0
A57: Licences SFD | B57: M F | C57: =C45*Hypothèses!$C$44*12 -> 0 | D57: =D45*Hypothèses!$C$44*12 -> 0 | E57: =E45*Hypothèses!$C$44*12 -> 0 | F57: =F45*Hypothèses!$C$44*12 -> 0 | G57: =G45*Hypothèses!$C$44*12 -> 0
A58: Frais d'apport de crédit (SFD) | B58: M F | C58: =C45*Hypothèses!C$18*Hypothèses!$C$35*Hypothèses!$C$40 -> 0 | D58: =D45*Hypothèses!D$18*Hypothèses!$C$35*Hypothèses!$C$40 -> 0 | E58: =E45*Hypothèses!E$18*Hypothèses!$C$35*Hypothèses!$C$40 -> 0 | F58: =F45*Hypothèses!F$18*Hypothèses!$C$35*Hypothèses!$C$40 -> 0 | G58: =G45*Hypothèses!G$18*Hypothèses!$C$35*Hypothèses!$C$40 -> 0
A59: Chiffre d'affaires | B59: M F | C59: =SUM(C50:C58) -> 23336100 | D59: =SUM(D50:D58) -> 85004550 | E59: =SUM(E50:E58) -> 230609700 | F59: =SUM(F50:F58) -> 450611100 | G59: =SUM(G50:G58) -> 799048800
A60: Coûts variables
A61: Frais Mobile Money (entrée + sortie) | B61: M F | C61: =C47*(Hypothèses!$C$24+Hypothèses!$C$25)*(1-Hypothèses!$D$61)*(1-Hypothèses!$D$70) -> 14802750 | D61: =D47*(Hypothèses!$C$24+Hypothèses!$C$25)*(1-Hypothèses!$D$61)*(1-Hypothèses!$D$70) -> 50068125 | E61: =E47*(Hypothèses!$C$24+Hypothèses!$C$25)*(1-Hypothèses!$D$61)*(1-Hypothèses!$D$70) -> 130797450 | F61: =F47*(Hypothèses!$C$24+Hypothèses!$C$25)*(1-Hypothèses!$D$61)*(1-Hypothèses!$D$70) -> 244980450 | G61: =G47*(Hypothèses!$C$24+Hypothèses!$C$25)*(1-Hypothèses!$D$61)*(1-Hypothèses!$D$70) -> 413829000 | H61: seul l'argent qui entre et ressort par Mobile Money coûte des frais
A62: SMS, hébergement | B62: M F | C62: =(C44+0.5*C45)*(Hypothèses!$C$26+Hypothèses!$C$27) -> 2089800 | D62: =(D44+0.5*D45)*(Hypothèses!$C$26+Hypothèses!$C$27) -> 8010900 | E62: =(E44+0.5*E45)*(Hypothèses!$C$26+Hypothèses!$C$27) -> 21197700 | F62: =(F44+0.5*F45)*(Hypothèses!$C$26+Hypothèses!$C$27) -> 40532400 | G62: =(G44+0.5*G45)*(Hypothèses!$C$26+Hypothèses!$C$27) -> 71271900 | H62: membres SFD comptés à 50 %
A63: KYC | B63: M F | C63: =C44*Hypothèses!$C$29*Hypothèses!$C$28 -> 967500 | D63: =MAX(0,D44-C44)*Hypothèses!$C$29*Hypothèses!$C$28 -> 2741250 | E63: =MAX(0,E44-D44)*Hypothèses!$C$29*Hypothèses!$C$28 -> 6105000 | F63: =MAX(0,F44-E44)*Hypothèses!$C$29*Hypothèses!$C$28 -> 8951250 | G63: =MAX(0,G44-F44)*Hypothèses!$C$29*Hypothèses!$C$28 -> 14231250
A64: Garantie de première perte (crédit) | B64: M F | C64: =C48*Hypothèses!$C$38*Hypothèses!$C$39 -> 0 | D64: =D48*Hypothèses!$C$38*Hypothèses!$C$39 -> 0 | E64: =E48*Hypothèses!$C$38*Hypothèses!$C$39 -> 0 | F64: =F48*Hypothèses!$C$38*Hypothèses!$C$39 -> 0 | G64: =G48*Hypothèses!$C$38*Hypothèses!$C$39 -> 0
A65: Acquisition | B65: M F | C65: =C44*Hypothèses!$D$68+C45*Hypothèses!$D$69 -> 9288000 | D65: =MAX(0,D44-C44)*Hypothèses!$D$68+MAX(0,D45-C45)*Hypothèses!$D$69 -> 26316000 | E65: =MAX(0,E44-D44)*Hypothèses!$D$68+MAX(0,E45-D45)*Hypothèses!$D$69 -> 58608000 | F65: =MAX(0,F44-E44)*Hypothèses!$D$68+MAX(0,F45-E45)*Hypothèses!$D$69 -> 85932000 | G65: =MAX(0,G44-F44)*Hypothèses!$D$68+MAX(0,G45-F45)*Hypothèses!$D$69 -> 136620000 | H65: nouveaux membres × CAC
A66: Total coûts variables | B66: M F | C66: =SUM(C61:C65) -> 27148050 | D66: =SUM(D61:D65) -> 87136275 | E66: =SUM(E61:E65) -> 216708150 | F66: =SUM(F61:F65) -> 380396100 | G66: =SUM(G61:G65) -> 635952150
A67: Marge sur coûts variables | B67: M F | C67: =C59-C66 -> -3811950 | D67: =D59-D66 -> -2131725 | E67: =E59-E66 -> 13901550 | F67: =F59-F66 -> 70215000 | G67: =G59-G66 -> 163096650
A68: Coûts fixes
A69: Siège (équipe + charges fixes) | B69: M F | C69: =(Hypothèses!C$20*Hypothèses!$C$46+Hypothèses!$C$49)*(1-Hypothèses!$D$72) -> 88000000 | D69: =(Hypothèses!D$20*Hypothèses!$C$46+Hypothèses!$C$49)*(1-Hypothèses!$D$72) -> 112000000 | E69: =(Hypothèses!E$20*Hypothèses!$C$46+Hypothèses!$C$49)*(1-Hypothèses!$D$72) -> 136000000 | F69: =(Hypothèses!F$20*Hypothèses!$C$46+Hypothèses!$C$49)*(1-Hypothèses!$D$72) -> 160000000 | G69: =(Hypothèses!G$20*Hypothèses!$C$46+Hypothèses!$C$49)*(1-Hypothèses!$D$72) -> 184000000
A70: Pays ouverts (équipes + marque) | B70: M F | C70: =Déploiement!C$39*(Hypothèses!$C$47+Hypothèses!$C$48)*Hypothèses!$D$58+Déploiement!C$39*Hypothèses!$C$47*0.5*(1-Hypothèses!$D$58) -> 57000000 | D70: =Déploiement!D$39*(Hypothèses!$C$47+Hypothèses!$C$48)*Hypothèses!$D$58+Déploiement!D$39*Hypothèses!$C$47*0.5*(1-Hypothèses!$D$58) -> 57000000 | E70: =Déploiement!E$39*(Hypothèses!$C$47+Hypothèses!$C$48)*Hypothèses!$D$58+Déploiement!E$39*Hypothèses!$C$47*0.5*(1-Hypothèses!$D$58) -> 114000000 | F70: =Déploiement!F$39*(Hypothèses!$C$47+Hypothèses!$C$48)*Hypothèses!$D$58+Déploiement!F$39*Hypothèses!$C$47*0.5*(1-Hypothèses!$D$58) -> 171000000 | G70: =Déploiement!G$39*(Hypothèses!$C$47+Hypothèses!$C$48)*Hypothèses!$D$58+Déploiement!G$39*Hypothèses!$C$47*0.5*(1-Hypothèses!$D$58) -> 285000000 | H70: B2C : coût pays complet ; modèle E (sans B2C) : demi-coût, pas de marque
A71: Équipes crédit / B2B | B71: M F | C71: =Hypothèses!$C$50*Hypothèses!C$21*Hypothèses!$D$65+Hypothèses!$C$51*IF(Hypothèses!$D$67>0,1,0) -> 0 | D71: =Hypothèses!$C$50*Hypothèses!D$21*Hypothèses!$D$65+Hypothèses!$C$51*IF(Hypothèses!$D$67>0,1,0) -> 0 | E71: =Hypothèses!$C$50*Hypothèses!E$21*Hypothèses!$D$65+Hypothèses!$C$51*IF(Hypothèses!$D$67>0,1,0) -> 0 | F71: =Hypothèses!$C$50*Hypothèses!F$21*Hypothèses!$D$65+Hypothèses!$C$51*IF(Hypothèses!$D$67>0,1,0) -> 0 | G71: =Hypothèses!$C$50*Hypothèses!G$21*Hypothèses!$D$65+Hypothèses!$C$51*IF(Hypothèses!$D$67>0,1,0) -> 0
A72: Total coûts fixes | B72: M F | C72: =SUM(C69:C71) -> 145000000 | D72: =SUM(D69:D71) -> 169000000 | E72: =SUM(E69:E71) -> 250000000 | F72: =SUM(F69:F71) -> 331000000 | G72: =SUM(G69:G71) -> 469000000
A73: Résultat et trésorerie
A74: EBITDA | B74: M F | C74: =C67-C72 -> -148811950 | D74: =D67-D72 -> -171131725 | E74: =E67-E72 -> -236098450 | F74: =F67-F72 -> -260785000 | G74: =G67-G72 -> -305903350
A75: Impôt (sur EBITDA − amortissement si positif) | B75: M F | C75: =MAX(0,C74-Hypothèses!$C$52/3*IF(0<3,1,0))*Hypothèses!$C$53 -> 0 | D75: =MAX(0,D74-Hypothèses!$C$52/3*IF(1<3,1,0))*Hypothèses!$C$53 -> 0 | E75: =MAX(0,E74-Hypothèses!$C$52/3*IF(2<3,1,0))*Hypothèses!$C$53 -> 0 | F75: =MAX(0,F74-Hypothèses!$C$52/3*IF(3<3,1,0))*Hypothèses!$C$53 -> 0 | G75: =MAX(0,G74-Hypothèses!$C$52/3*IF(4<3,1,0))*Hypothèses!$C$53 -> 0
A76: Flux de trésorerie | B76: M F | C76: =C74-C75-IF(0=0,Hypothèses!$C$52,0) -> -193811950 | D76: =D74-D75-IF(1=0,Hypothèses!$C$52,0) -> -171131725 | E76: =E74-E75-IF(2=0,Hypothèses!$C$52,0) -> -236098450 | F76: =F74-F75-IF(3=0,Hypothèses!$C$52,0) -> -260785000 | G76: =G74-G75-IF(4=0,Hypothèses!$C$52,0) -> -305903350
A77: Trésorerie cumulée | B77: M F | C77: =C76 -> -193811950 | D77: =C77+D76 -> -364943675 | E77: =D77+E76 -> -601042125 | F77: =E77+F76 -> -861827125 | G77: =F77+G76 -> -1167730475
A78: EBITDA positif (1 = oui) | B78: indicateur | C78: =IF(C74>0,1,0) -> 0 | D78: =IF(D74>0,1,0) -> 0 | E78: =IF(E74>0,1,0) -> 0 | F78: =IF(F74>0,1,0) -> 0 | G78: =IF(G74>0,1,0) -> 0
A79: Marge sur coûts variables par membre (hors acquisition) | B79: F | C79: =IF((C44+C45)=0,0,(C67+C65)/(C44+C45)) -> 707.5 | D79: =IF((D44+D45)=0,0,(D67+D65)/(D44+D45)) -> 815.1087 | E79: =IF((E44+E45)=0,0,(E67+E65)/(E44+E45)) -> 923.57088 | F79: =IF((F44+F45)=0,0,(F67+F65)/(F44+F45)) -> 1040.1479 | G79: =IF((G44+G45)=0,0,(G67+G65)/(G44+G45)) -> 1135.4194 | H79: par membre (B2C + B2B) et par an
A81: Modèle C — Freemium abonnements
A82: Membres actifs B2C | B82: membres | C82: =Déploiement!C$36*Hypothèses!$E$58 -> 7740 | D82: =Déploiement!D$36*Hypothèses!$E$58 -> 29670 | E82: =Déploiement!E$36*Hypothèses!$E$58 -> 78510 | F82: =Déploiement!F$36*Hypothèses!$E$58 -> 150120 | G82: =Déploiement!G$36*Hypothèses!$E$58 -> 263970
A83: Membres SFD gérés (B2B) | B83: membres | C83: =Déploiement!C$40*Hypothèses!$E$67 -> 0 | D83: =Déploiement!D$40*Hypothèses!$E$67 -> 0 | E83: =Déploiement!E$40*Hypothèses!$E$67 -> 0 | F83: =Déploiement!F$40*Hypothèses!$E$67 -> 0 | G83: =Déploiement!G$40*Hypothèses!$E$67 -> 0
A84: Cotisations B2C (= pots versés) | B84: M F | C84: =Déploiement!C$38*Hypothèses!$E$58 -> 1161000000 | D84: =Déploiement!D$38*Hypothèses!$E$58 -> 4450500000 | E84: =Déploiement!E$38*Hypothèses!$E$58 -> 12456900000 | F84: =Déploiement!F$38*Hypothèses!$E$58 -> 25126200000 | G84: =Déploiement!G$38*Hypothèses!$E$58 -> 45981000000
A85: Pots retirés vers Mobile Money | B85: M F | C85: =C84*(1-MIN(0.9,Hypothèses!C$17+Hypothèses!$E$71)) -> 986850000 | D85: =D84*(1-MIN(0.9,Hypothèses!D$17+Hypothèses!$E$71)) -> 3337875000 | E85: =E84*(1-MIN(0.9,Hypothèses!E$17+Hypothèses!$E$71)) -> 8719830000 | F85: =F84*(1-MIN(0.9,Hypothèses!F$17+Hypothèses!$E$71)) -> 16332030000 | G85: =G84*(1-MIN(0.9,Hypothèses!G$17+Hypothèses!$E$71)) -> 27588600000 | H85: cotisations × (1 − recirculation) : ce qui entre par Mobile Money finit par ressortir
A86: Crédits versés (via SFD) | B86: M F | C86: =C82*Hypothèses!C$18*Hypothèses!$C$35*Hypothèses!$E$65 -> 0 | D86: =D82*Hypothèses!D$18*Hypothèses!$C$35*Hypothèses!$E$65 -> 0 | E86: =E82*Hypothèses!E$18*Hypothèses!$C$35*Hypothèses!$E$65 -> 0 | F86: =F82*Hypothèses!F$18*Hypothèses!$C$35*Hypothèses!$E$65 -> 0 | G86: =G82*Hypothèses!G$18*Hypothèses!$C$35*Hypothèses!$E$65 -> 0
A87: Revenus
A88: Commission sur les pots | B88: M F | C88: =C84*Hypothèses!$E$59 -> 0 | D88: =D84*Hypothèses!$E$59 -> 0 | E88: =E84*Hypothèses!$E$59 -> 0 | F88: =F84*Hypothèses!$E$59 -> 0 | G88: =G84*Hypothèses!$E$59 -> 0
A89: Frais de retrait | B89: M F | C89: =C85*Hypothèses!$E$60 -> 0 | D89: =D85*Hypothèses!$E$60 -> 0 | E89: =E85*Hypothèses!$E$60 -> 0 | F89: =F85*Hypothèses!$E$60 -> 0 | G89: =G85*Hypothèses!$E$60 -> 0
A90: Abonnements Organisateur Pro | B90: M F | C90: =C82/Hypothèses!$C$30*Hypothèses!$E$62*Hypothèses!$C$31*12 -> 3870000 | D90: =D82/Hypothèses!$C$30*Hypothèses!$E$62*Hypothèses!$C$31*12 -> 14835000 | E90: =E82/Hypothèses!$C$30*Hypothèses!$E$62*Hypothèses!$C$31*12 -> 39255000 | F90: =F82/Hypothèses!$C$30*Hypothèses!$E$62*Hypothèses!$C$31*12 -> 75060000 | G90: =G82/Hypothèses!$C$30*Hypothèses!$E$62*Hypothèses!$C$31*12 -> 131985000 | H90: groupes × conversion × prix × 12
A91: Abonnements Smart Tontine+ | B91: M F | C91: =C82*Hypothèses!$E$63*Hypothèses!$C$32*12 -> 2322000 | D91: =D82*Hypothèses!$E$63*Hypothèses!$C$32*12 -> 8901000 | E91: =E82*Hypothèses!$E$63*Hypothèses!$C$32*12 -> 23553000 | F91: =F82*Hypothèses!$E$63*Hypothèses!$C$32*12 -> 45036000 | G91: =G82*Hypothèses!$E$63*Hypothèses!$C$32*12 -> 79191000
A92: Revenus du float | B92: M F | C92: =C82*Hypothèses!$C$33*Hypothèses!$C$34*Hypothèses!$E$64 -> 1857600 | D92: =D82*Hypothèses!$C$33*Hypothèses!$C$34*Hypothèses!$E$64 -> 7120800 | E92: =E82*Hypothèses!$C$33*Hypothèses!$C$34*Hypothèses!$E$64 -> 18842400 | F92: =F82*Hypothèses!$C$33*Hypothèses!$C$34*Hypothèses!$E$64 -> 36028800 | G92: =G82*Hypothèses!$C$33*Hypothèses!$C$34*Hypothèses!$E$64 -> 63352800
A93: Part des intérêts de crédit | B93: M F | C93: =C86*Hypothèses!$C$36*Hypothèses!$C$37 -> 0 | D93: =D86*Hypothèses!$C$36*Hypothèses!$C$37 -> 0 | E93: =E86*Hypothèses!$C$36*Hypothèses!$C$37 -> 0 | F93: =F86*Hypothèses!$C$36*Hypothèses!$C$37 -> 0 | G93: =G86*Hypothèses!$C$36*Hypothèses!$C$37 -> 0
A94: Commissions d'assurance | B94: M F | C94: =C82*Hypothèses!$C$41*Hypothèses!$C$42*Hypothèses!$C$43*Hypothèses!$E$66 -> 0 | D94: =D82*Hypothèses!$C$41*Hypothèses!$C$42*Hypothèses!$C$43*Hypothèses!$E$66 -> 0 | E94: =E82*Hypothèses!$C$41*Hypothèses!$C$42*Hypothèses!$C$43*Hypothèses!$E$66 -> 0 | F94: =F82*Hypothèses!$C$41*Hypothèses!$C$42*Hypothèses!$C$43*Hypothèses!$E$66 -> 0 | G94: =G82*Hypothèses!$C$41*Hypothèses!$C$42*Hypothèses!$C$43*Hypothèses!$E$66 -> 0
A95: Licences SFD | B95: M F | C95: =C83*Hypothèses!$C$44*12 -> 0 | D95: =D83*Hypothèses!$C$44*12 -> 0 | E95: =E83*Hypothèses!$C$44*12 -> 0 | F95: =F83*Hypothèses!$C$44*12 -> 0 | G95: =G83*Hypothèses!$C$44*12 -> 0
A96: Frais d'apport de crédit (SFD) | B96: M F | C96: =C83*Hypothèses!C$18*Hypothèses!$C$35*Hypothèses!$C$40 -> 0 | D96: =D83*Hypothèses!D$18*Hypothèses!$C$35*Hypothèses!$C$40 -> 0 | E96: =E83*Hypothèses!E$18*Hypothèses!$C$35*Hypothèses!$C$40 -> 0 | F96: =F83*Hypothèses!F$18*Hypothèses!$C$35*Hypothèses!$C$40 -> 0 | G96: =G83*Hypothèses!G$18*Hypothèses!$C$35*Hypothèses!$C$40 -> 0
A97: Chiffre d'affaires | B97: M F | C97: =SUM(C88:C96) -> 8049600 | D97: =SUM(D88:D96) -> 30856800 | E97: =SUM(E88:E96) -> 81650400 | F97: =SUM(F88:F96) -> 156124800 | G97: =SUM(G88:G96) -> 274528800
A98: Coûts variables
A99: Frais Mobile Money (entrée + sortie) | B99: M F | C99: =C85*(Hypothèses!$C$24+Hypothèses!$C$25)*(1-Hypothèses!$E$61)*(1-Hypothèses!$E$70) -> 0 | D99: =D85*(Hypothèses!$C$24+Hypothèses!$C$25)*(1-Hypothèses!$E$61)*(1-Hypothèses!$E$70) -> 0 | E99: =E85*(Hypothèses!$C$24+Hypothèses!$C$25)*(1-Hypothèses!$E$61)*(1-Hypothèses!$E$70) -> 0 | F99: =F85*(Hypothèses!$C$24+Hypothèses!$C$25)*(1-Hypothèses!$E$61)*(1-Hypothèses!$E$70) -> 0 | G99: =G85*(Hypothèses!$C$24+Hypothèses!$C$25)*(1-Hypothèses!$E$61)*(1-Hypothèses!$E$70) -> 0 | H99: seul l'argent qui entre et ressort par Mobile Money coûte des frais
A100: SMS, hébergement | B100: M F | C100: =(C82+0.5*C83)*(Hypothèses!$C$26+Hypothèses!$C$27) -> 2089800 | D100: =(D82+0.5*D83)*(Hypothèses!$C$26+Hypothèses!$C$27) -> 8010900 | E100: =(E82+0.5*E83)*(Hypothèses!$C$26+Hypothèses!$C$27) -> 21197700 | F100: =(F82+0.5*F83)*(Hypothèses!$C$26+Hypothèses!$C$27) -> 40532400 | G100: =(G82+0.5*G83)*(Hypothèses!$C$26+Hypothèses!$C$27) -> 71271900 | H100: membres SFD comptés à 50 %
A101: KYC | B101: M F | C101: =C82*Hypothèses!$C$29*Hypothèses!$C$28 -> 967500 | D101: =MAX(0,D82-C82)*Hypothèses!$C$29*Hypothèses!$C$28 -> 2741250 | E101: =MAX(0,E82-D82)*Hypothèses!$C$29*Hypothèses!$C$28 -> 6105000 | F101: =MAX(0,F82-E82)*Hypothèses!$C$29*Hypothèses!$C$28 -> 8951250 | G101: =MAX(0,G82-F82)*Hypothèses!$C$29*Hypothèses!$C$28 -> 14231250
A102: Garantie de première perte (crédit) | B102: M F | C102: =C86*Hypothèses!$C$38*Hypothèses!$C$39 -> 0 | D102: =D86*Hypothèses!$C$38*Hypothèses!$C$39 -> 0 | E102: =E86*Hypothèses!$C$38*Hypothèses!$C$39 -> 0 | F102: =F86*Hypothèses!$C$38*Hypothèses!$C$39 -> 0 | G102: =G86*Hypothèses!$C$38*Hypothèses!$C$39 -> 0
A103: Acquisition | B103: M F | C103: =C82*Hypothèses!$E$68+C83*Hypothèses!$E$69 -> 10836000 | D103: =MAX(0,D82-C82)*Hypothèses!$E$68+MAX(0,D83-C83)*Hypothèses!$E$69 -> 30702000 | E103: =MAX(0,E82-D82)*Hypothèses!$E$68+MAX(0,E83-D83)*Hypothèses!$E$69 -> 68376000 | F103: =MAX(0,F82-E82)*Hypothèses!$E$68+MAX(0,F83-E83)*Hypothèses!$E$69 -> 100254000 | G103: =MAX(0,G82-F82)*Hypothèses!$E$68+MAX(0,G83-F83)*Hypothèses!$E$69 -> 159390000 | H103: nouveaux membres × CAC
...

Sheet Sensibilité G
A1: Modèle G — Sensibilité de l'EBITDA 2031 (M FCFA)
A2: Adoption (lignes, en % de l'hypothèse) × coût Mobile Money entrée + sortie (colonnes) · approximation linéaire autour du scénario central
A4: Adoption ↓ / coût Mobile Money → | B4: 0.006 | C4: 0.009 | D4: 0.012 | E4: 0.015 | F4: 0.02
A5: 0.5 | B5: =($A5)*(Modèles!$G$257+Modèles!$G$251)-$A5*Modèles!$G$237*B$4-Modèles!$G$262 -> -106699390 | C5: =($A5)*(Modèles!$G$257+Modèles!$G$251)-$A5*Modèles!$G$237*C$4-Modèles!$G$262 -> -148082290 | D5: =($A5)*(Modèles!$G$257+Modèles!$G$251)-$A5*Modèles!$G$237*D$4-Modèles!$G$262 -> -189465190 | E5: =($A5)*(Modèles!$G$257+Modèles!$G$251)-$A5*Modèles!$G$237*E$4-Modèles!$G$262 -> -230848090 | F5: =($A5)*(Modèles!$G$257+Modèles!$G$251)-$A5*Modèles!$G$237*F$4-Modèles!$G$262 -> -299819590
A6: 0.75 | B6: =($A6)*(Modèles!$G$257+Modèles!$G$251)-$A6*Modèles!$G$237*B$4-Modèles!$G$262 -> 83550915 | C6: =($A6)*(Modèles!$G$257+Modèles!$G$251)-$A6*Modèles!$G$237*C$4-Modèles!$G$262 -> 21476565 | D6: =($A6)*(Modèles!$G$257+Modèles!$G$251)-$A6*Modèles!$G$237*D$4-Modèles!$G$262 -> -40597785 | E6: =($A6)*(Modèles!$G$257+Modèles!$G$251)-$A6*Modèles!$G$237*E$4-Modèles!$G$262 -> -102672135 | F6: =($A6)*(Modèles!$G$257+Modèles!$G$251)-$A6*Modèles!$G$237*F$4-Modèles!$G$262 -> -206129385
A7: 1 | B7: =($A7)*(Modèles!$G$257+Modèles!$G$251)-$A7*Modèles!$G$237*B$4-Modèles!$G$262 -> 273801220 | C7: =($A7)*(Modèles!$G$257+Modèles!$G$251)-$A7*Modèles!$G$237*C$4-Modèles!$G$262 -> 191035420 | D7: =($A7)*(Modèles!$G$257+Modèles!$G$251)-$A7*Modèles!$G$237*D$4-Modèles!$G$262 -> 108269620 | E7: =($A7)*(Modèles!$G$257+Modèles!$G$251)-$A7*Modèles!$G$237*E$4-Modèles!$G$262 -> 25503820 | F7: =($A7)*(Modèles!$G$257+Modèles!$G$251)-$A7*Modèles!$G$237*F$4-Modèles!$G$262 -> -112439180
A8: 1.25 | B8: =($A8)*(Modèles!$G$257+Modèles!$G$251)-$A8*Modèles!$G$237*B$4-Modèles!$G$262 -> 464051525 | C8: =($A8)*(Modèles!$G$257+Modèles!$G$251)-$A8*Modèles!$G$237*C$4-Modèles!$G$262 -> 360594275 | D8: =($A8)*(Modèles!$G$257+Modèles!$G$251)-$A8*Modèles!$G$237*D$4-Modèles!$G$262 -> 257137025 | E8: =($A8)*(Modèles!$G$257+Modèles!$G$251)-$A8*Modèles!$G$237*E$4-Modèles!$G$262 -> 153679775 | F8: =($A8)*(Modèles!$G$257+Modèles!$G$251)-$A8*Modèles!$G$237*F$4-Modèles!$G$262 -> -18748975
A10: Le scénario central de G correspond à la ligne 100 % et à la colonne 0,9 % (1,5 % − 40 %). L'effet des membres B2B est lui aussi mis à l'échelle (approximation prudente).
